repomate_plug/__init__.py
repomate_plug/__version.py
repomate_plug/corehooks.py
repomate_plug/exception.py
repomate_plug/exthooks.py
repomate_plug/pluginmeta.py
repomate_plug/util.py
repomate_plug-0.4.1.dist-info/LICENSE
repomate_plug-0.4.1.dist-info/METADATA
repomate_plug-0.4.1.dist-info/WHEEL
repomate_plug-0.4.1.dist-info/top_level.txt
repomate_plug-0.4.1.dist-info/RECORD
