Metadata-Version: 2.1
Name: repomate-plug
Version: 0.4.1
Summary: Core components for plugin system in repomate
Home-page: https://github.com/slarse/repomate-plug
Author: Simon Larsén
Author-email: slarse@kth.se
License: MIT
Download-URL: https://github.com/slarse/repomate-plug/archive/v0.4.1.tar.gz
Platform: UNKNOWN
Classifier: Development Status :: 4 - Beta
Classifier: Intended Audience :: Education
Classifier: Programming Language :: Python :: 3.5
Classifier: Programming Language :: Python :: 3.6
Classifier: Programming Language :: Python :: 3.7
Classifier: Programming Language :: Python :: Implementation :: CPython
Classifier: License :: OSI Approved :: MIT License
Classifier: Operating System :: POSIX
Requires-Dist: pluggy (>=0.8.0)
Provides-Extra: test
Requires-Dist: pytest (>=4.0.0) ; extra == 'test'
Requires-Dist: pytest-cov ; extra == 'test'
Requires-Dist: codecov ; extra == 'test'
